molab_ext/__init__.py
molab_ext/lab_extension.py
molab_ext_v1/__init__.py
molab_ext_v1/lab_extension.py
molab_ext-0.1.5.dist-info/METADATA
molab_ext-0.1.5.dist-info/WHEEL
molab_ext-0.1.5.dist-info/top_level.txt
molab_ext-0.1.5.dist-info/RECORD
